{
  "projectDetails": {
    "projectIds": "",
    "builderIds": "",
    "address": {
      "location": "",
      "city": ""
    },
    "projectType": {
      "apartment": "",
      "villa": "",
      "rowHouse": "",
      "studioApartment": "",
      "servicedApartment": ""
    },
    "carParking": "",
    "vastuCompliant": ""
  },
  "projectStatus": {
    "underConstruction": "",
    "readyToMove": ""
  },
  "sportsActivities": {
    "cricket": "",
    "football": "",
    "tennis": "",
    "basketball": "",
    "pitchAndPutt": "",
    "skatingRink": "",
    "volleyball": "",
    "amphitheatre": "",
    "badminton": "",
    "tableTennis": "",
    "squash": "",
    "swimmingPool": "",
    "poolTable": "",
    "snookerTable": "",
    "bowlingAlley": "",
    "joggingTrack": ""
  },
  "clubHouse": {
    "multiPurposeHall": "",
    "restaurant": "",
    "yogaRoom": "",
    "aerobicsRoom": "",
    "danceRoom": "",
    "musicRoom": "",
    "salon": "",
    "spa": "",
    "gym": "",
    "videoGames": "",
    "miniTheatre": "",
    "kidsZone": "",
    "bar": "",
    "cafe": "",
    "businessCentre": "",
    "guestRoom": "",
    "steamRoom": "",
    "saunaRoom": "",
    "jacuzzi": ""
  },
  "rating": "",
  "top": "",
  "other": {
    "powerBackup": "",
    "maintenance": "",
    "petFriendly": "",
    "wheelchairFriendly": ""
  },
  "security": {
    "mainGate": {
      "guards": "",
      "boomBarriers": "",
      "intercom": "",
      "cctv": ""
    },
    "tower": {
      "accessControlled": "",
      "guards": "",
      "cctv": ""
    }
  },
  "configurations": {
    "propertyType": "",
    "type": "",
    "price": "",
    "priceLevel" : "",
    "area": "",
    "areaLevel" : "",
    "storeRoom": "",
    "servantRoom": ""
  },
  "specifications": {
    "showerCubicle": "",
    "homeAutomation": "",
    "vrvAirConditioning": "",
    "kitchenAppliances": "",
    "kitchenOtg": "",
    "bathTub": "",
    "kitchenModular": "",
    "kitchenDishWasher": "",
    "airConditioning": "",
    "flooringMasterBedrooms": "",
    "kitchenChimney": "",
    "flooringLivingDining": "",
    "kitchenMicrowaveOven": "",
    "kitchenRefrigerator": "",
    "flooringOtherBedrooms": "",
    "kitchenHob": "",
    "fullyFurnished": "",
    "wardrobes": ""
  }
}